final_complete_server.py
main.py
core/__init__.py
core/ai_guidance_enhancer.py
core/ai_interface.py
core/docx_processor.py
core/enhanced_docx_processor.py
core/enhanced_state_manager.py
core/file_path_utils.py
core/fixed_docx_processor.py
core/font_processor.py
core/image_processor.py
core/intelligent_table_analyzer.py
core/intelligent_tool_planner.py
core/json_validation_engine.py
core/models.py
core/oss_processor.py
core/smart_suggestion_engine.py
core/state_machine.py
core/state_manager.py
core/table_structure_extractor.py
core/template_engine.py
core/universal_table_filler.py
core/workflow_engine.py
docx_mcp-0.1.7.dist-info/licenses/LICENSE
docx_mcp-0.1.7.dist-info/METADATA
docx_mcp-0.1.7.dist-info/WHEEL
docx_mcp-0.1.7.dist-info/entry_points.txt
docx_mcp-0.1.7.dist-info/top_level.txt
docx_mcp-0.1.7.dist-info/RECORD
